pyteams/__init__.py
pyteams/main.py
pyteams/webhooks.py
pyteams-1.0.2.dist-info/METADATA
pyteams-1.0.2.dist-info/RECORD
pyteams-1.0.2.dist-info/WHEEL
pyteams-1.0.2.dist-info/entry_points.txt
pyteams-1.0.2.dist-info/top_level.txt
pyteams-1.0.2.dist-info/zip-safe
